odoo/addons/analytic_operating_unit/README.rst
odoo/addons/analytic_operating_unit/__init__.py
odoo/addons/analytic_operating_unit/__manifest__.py
odoo/addons/analytic_operating_unit/i18n/analytic_operating_unit.pot
odoo/addons/analytic_operating_unit/i18n/es_MX.po
odoo/addons/analytic_operating_unit/models/__init__.py
odoo/addons/analytic_operating_unit/models/account_analytic_account.py
odoo/addons/analytic_operating_unit/security/analytic_account_security.xml
odoo/addons/analytic_operating_unit/static/description/icon.png
odoo/addons/analytic_operating_unit/views/analytic_account_view.xml
odoo13_addon_analytic_operating_unit-13.0.1.0.1.dist-info/METADATA
odoo13_addon_analytic_operating_unit-13.0.1.0.1.dist-info/WHEEL
odoo13_addon_analytic_operating_unit-13.0.1.0.1.dist-info/top_level.txt
odoo13_addon_analytic_operating_unit-13.0.1.0.1.dist-info/RECORD
